{
  "project_info": {
    "project_number": "315531009431",
    "firebase_url": "https://doctoroncall-f6f40.firebaseio.com",
    "project_id": "doctoroncall-f6f40",
    "storage_bucket": "doctoroncall-f6f40.appspot.com"
  },
  "client": [
    {
      "client_info": {
        "mobilesdk_app_id": "1:315531009431:android:6c23abbccd2f3284",
        "android_client_info": {
          "package_name": "com.saloni.doctoroncall"
        }
      },
      "oauth_client": [
        {
          "client_id": "315531009431-u3ulspund0l65teico89kctdlnf23ups.apps.googleusercontent.com",
          "client_type": 3
        }
      ],
      "api_key": [
        {
          "current_key": "AIzaSyD8Qhk-mtU7HPt83Otwaeh011iLxX5bqvo"
        }
      ],
      "services": {
        "analytics_service": {
          "status": 1
        },
        "appinvite_service": {
          "status": 1,
          "other_platform_oauth_client": []
        },
        "ads_service": {
          "status": 2
        }
      }
    }
  ],
  "configuration_version": "1"
}